enotipy/__init__.py
enotipy/enotipy.py
enotipy-1.0.3.dist-info/LICENSE
enotipy-1.0.3.dist-info/METADATA
enotipy-1.0.3.dist-info/WHEEL
enotipy-1.0.3.dist-info/entry_points.txt
enotipy-1.0.3.dist-info/top_level.txt
enotipy-1.0.3.dist-info/RECORD
