Metadata-Version: 2.1
Name: enotipy
Version: 1.0.3
Summary: ENotipy is a package to wrap your code and email you upon it's completion
Home-page: https://github.com/awa1k3r/Notipy
Author: Anthony Walker
Author-email: dev.notipy@gmail.com
License: BSD 3-clause "New" or "Revised License"
Platform: UNKNOWN
Classifier: Programming Language :: Python :: 3
Classifier: License :: OSI Approved :: BSD License
Classifier: Operating System :: OS Independent
Requires-Python: >=3.6
